django_password_validators/__init__.py
django_password_validators/models.py
django_password_validators/settings.py
django_password_validators/locale/ar/LC_MESSAGES/django.mo
django_password_validators/locale/ar/LC_MESSAGES/django.po
django_password_validators/locale/de/LC_MESSAGES/django.mo
django_password_validators/locale/de/LC_MESSAGES/django.po
django_password_validators/locale/en/LC_MESSAGES/django.mo
django_password_validators/locale/en/LC_MESSAGES/django.po
django_password_validators/locale/es/LC_MESSAGES/django.mo
django_password_validators/locale/es/LC_MESSAGES/django.po
django_password_validators/locale/fi/LC_MESSAGES/django.mo
django_password_validators/locale/fi/LC_MESSAGES/django.po
django_password_validators/locale/fr/LC_MESSAGES/django.mo
django_password_validators/locale/fr/LC_MESSAGES/django.po
django_password_validators/locale/it/LC_MESSAGES/django.mo
django_password_validators/locale/it/LC_MESSAGES/django.po
django_password_validators/locale/pl/LC_MESSAGES/django.mo
django_password_validators/locale/pl/LC_MESSAGES/django.po
django_password_validators/locale/zh_Hans/LC_MESSAGES/django.mo
django_password_validators/locale/zh_Hans/LC_MESSAGES/django.po
django_password_validators/password_character_requirements/__init__.py
django_password_validators/password_character_requirements/password_validation.py
django_password_validators/password_history/__init__.py
django_password_validators/password_history/admin.py
django_password_validators/password_history/apps.py
django_password_validators/password_history/hashers.py
django_password_validators/password_history/models.py
django_password_validators/password_history/password_validation.py
django_password_validators/password_history/migrations/0001_initial.py
django_password_validators/password_history/migrations/0002_auto_20180424_1422.py
django_password_validators/password_history/migrations/0003_auto_20201206_1357.py
django_password_validators/password_history/migrations/__init__.py
django_password_validators-1.7.3.dist-info/LICENSE.txt
django_password_validators-1.7.3.dist-info/METADATA
django_password_validators-1.7.3.dist-info/WHEEL
django_password_validators-1.7.3.dist-info/top_level.txt
django_password_validators-1.7.3.dist-info/RECORD
