Metadata-Version: 2.1
Name: django-password-validators
Version: 1.7.3
Summary: Additional libraries for validating passwords in Django.
Home-page: https://github.com/fizista/django-password-validators
Author: Wojciech Banas
Author-email: fizista@gmail.com
License: BSD
Keywords: django password validator
Classifier: Development Status :: 5 - Production/Stable
Classifier: Environment :: Web Environment
Classifier: Framework :: Django
Classifier: Intended Audience :: Developers
Classifier: License :: OSI Approved :: BSD License
Classifier: Programming Language :: Python :: 3.7
Classifier: Programming Language :: Python :: 3.8
Classifier: Programming Language :: Python :: 3.9
Classifier: Programming Language :: Python :: 3.10
Classifier: Programming Language :: Python :: 3.11
Classifier: Programming Language :: Python :: 3.12
Classifier: Programming Language :: Python
Classifier: Operating System :: OS Independent
Classifier: Topic :: Security
License-File: LICENSE.txt
Requires-Dist: django>=3.0
Provides-Extra: test
Requires-Dist: tox>=4.11; extra == "test"
Requires-Dist: bump-my-version>=0.12; extra == "test"
